{
  "instanceId": null,
  "productType": "НСО",
  "productCode": "03",
  "registerType": "12345678",
  "mdmCode": "15",
  "contractNumber": "77889",
  "contractDate": "2024-02-01",
  "priority": 1,
  "interestRatePenalty": 18.5,
  "minimalBalance": 10000000.00,
  "thresholdAmount": null,
  "accountingDetails": "Some accounting data",
  "rateType": 0,
  "taxPercentageRate": null,
  "technicalOverdraftLimitAmount": null,
  "contractId": 78563722,
  "branchCode": "0022",
  "isoCurrencyCode": "840",
  "urgencyCode": "00",
  "ReferenceCode": 453627,
  "additionalPropertiesVip": {
    "data": []
  },
  "instanceArrangements": [
  ]
}